client/TruinvestBroker.py
client/__init__.py
client/IciciTrading/IciciTrading.py
client/IciciTrading/__init__.py
client/KiteTrading/KiteTrading.py
client/KiteTrading/__init__.py
client/KotakTrading/KotakTrading.py
client/KotakTrading/__init__.py
client/MasterTrust/MasterTrust.py
client/MasterTrust/__init__.py
client/TradingInterface/TradingInterface.py
client/TradingInterface/__init__.py
client/uTradeBroker/__init__.py
client/uTradeBroker/uTradeBroker.py
truinvest_broker-1.1.0.dist-info/METADATA
truinvest_broker-1.1.0.dist-info/WHEEL
truinvest_broker-1.1.0.dist-info/top_level.txt
truinvest_broker-1.1.0.dist-info/RECORD
