Metadata-Version: 2.1
Name: truinvest-broker
Version: 1.1.0
Summary: Broker client Lib
Home-page: https://truinvest.ai/
Author: Anukkrit Shanker
Author-email: anukkrit@rebal.tech
Project-URL: Homepage, https://truinvest.ai/
Keywords: truinvest truinvest-broker
Classifier: Programming Language :: Python :: 3
Classifier: License :: OSI Approved :: MIT License
Classifier: Operating System :: OS Independent
Requires-Python: >=3.9
Requires-Dist: gitpython
Requires-Dist: kiteconnect
Requires-Dist: djangorestframework
Requires-Dist: requests
Requires-Dist: pandas
